[
  {
    "id": 1,
    "name": "Stereo Madness",
    "creator": "RobTop",
    "diff": "Easy",
    "section": "main",
    "filename": "stereo madness.gdr2",
    "size": 447,
    "ext": "gdr2",
    "gr2": "data:embedded",
    "uploadedAt": 1777720195618
  },
  {
    "id": 2,
    "name": "Back On Track",
    "creator": "RopTop",
    "diff": "Easy",
    "section": "main",
    "filename": "back on track.gdr2",
    "size": 421,
    "ext": "gdr2",
    "gr2": "data:embedded",
    "uploadedAt": 1777726262189
  },
  {
    "id": 4,
    "name": "Dry Out",
    "creator": "RopTop",
    "diff": "Normal",
    "section": "main",
    "filename": "dry out.gdr2",
    "size": 419,
    "ext": "gdr2",
    "gr2": "data:embedded",
    "uploadedAt": 1777726467179
  },
  {
    "id": 3,
    "name": "Polargiest",
    "creator": "RopTop",
    "diff": "Normal",
    "section": "main",
    "filename": "Polargiest.gdr2",
    "size": 453,
    "ext": "gdr2",
    "gr2": "data:embedded",
    "uploadedAt": 1777726507173
  },
  {
    "id": 5,
    "name": "Base After Base",
    "creator": "RopTop",
    "diff": "Hard",
    "section": "main",
    "filename": "base after base.gdr2",
    "size": 419,
    "ext": "gdr2",
    "gr2": "data:embedded",
    "uploadedAt": 1777726561272
  },
  {
    "id": 6,
    "name": "Cant Let Go",
    "creator": "RopTop",
    "diff": "Hard",
    "section": "main",
    "filename": "can't let go.gdr2",
    "size": 434,
    "ext": "gdr2",
    "gr2": "data:embedded",
    "uploadedAt": 1777732286466
  },
  {
    "id": 7,
    "name": "Jumper",
    "creator": "RopTop",
    "diff": "Harder",
    "section": "main",
    "filename": "jumper.gdr2",
    "size": 520,
    "ext": "gdr2",
    "gr2": "data:embedded",
    "uploadedAt": 1777732806524
  },
  {
    "id": 8,
    "name": "Time Machine",
    "creator": "RopTop",
    "diff": "Insane",
    "section": "main",
    "filename": "time machine.gdr2",
    "size": 455,
    "ext": "gdr2",
    "gr2": "data:embedded",
    "uploadedAt": 1777732834715
  },
  {
    "id": 9,
    "name": "Cycles",
    "creator": "RopTop",
    "diff": "Harder",
    "section": "main",
    "filename": "cycles.gdr2",
    "size": 386,
    "ext": "gdr2",
    "gr2": "data:embedded",
    "uploadedAt": 1777732874503
  },
  {
    "id": 10,
    "name": "Xtep",
    "creator": "RopTop",
    "diff": "Insane",
    "section": "main",
    "filename": "xtep.gdr2",
    "size": 459,
    "ext": "gdr2",
    "gr2": "data:embedded",
    "uploadedAt": 1777732901792
  },
  {
    "id": 11,
    "name": "Clutterfunk",
    "creator": "RobTop",
    "diff": "Insane",
    "section": "main",
    "filename": "clutterfunk.gdr2",
    "size": 513,
    "ext": "gdr2",
    "gr2": "data:embedded",
    "uploadedAt": 1777733284609
  },
  {
    "id": 12,
    "name": "Theory of everything",
    "creator": "RopTop",
    "diff": "Insane",
    "section": "main",
    "filename": "TOE I.gdr2",
    "size": 466,
    "ext": "gdr2",
    "gr2": "data:embedded",
    "uploadedAt": 1777733455984
  },
  {
    "id": 13,
    "name": "Electroman Adventures",
    "creator": "RopTop",
    "diff": "Insane",
    "section": "main",
    "filename": "Electroman adventures.gdr2",
    "size": 493,
    "ext": "gdr2",
    "gr2": "data:embedded",
    "uploadedAt": 1777733566273
  },
  {
    "id": 14,
    "name": "Clubstep",
    "creator": "RobTop",
    "diff": "Insane",
    "section": "main",
    "filename": "clubstep.gdr2",
    "size": 506,
    "ext": "gdr2",
    "gr2": "data:embedded",
    "uploadedAt": 1777733621479
  },
  {
    "id": 15,
    "name": "Electrodynamix",
    "creator": "RobTop",
    "diff": "Insane",
    "section": "main",
    "filename": "Electrodynamix.gdr2",
    "size": 448,
    "ext": "gdr2",
    "gr2": "data:embedded",
    "uploadedAt": 1777733671159
  },
  {
    "id": 16,
    "name": "Hexagon Force",
    "creator": "RobTop",
    "diff": "Insane",
    "section": "main",
    "filename": "hexagon force.gdr2",
    "size": 547,
    "ext": "gdr2",
    "gr2": "data:embedded",
    "uploadedAt": 1777733718057
  },
  {
    "id": 17,
    "name": "Blast Procsessing",
    "creator": "RobTop",
    "diff": "Harder",
    "section": "main",
    "filename": "blast procsessing.gdr2",
    "size": 650,
    "ext": "gdr2",
    "gr2": "data:embedded",
    "uploadedAt": 1777736107823
  },
  {
    "id": 18,
    "name": "Theory of everything 2",
    "creator": "RobTop",
    "diff": "Hard Demon",
    "section": "main",
    "filename": "TOE II.gdr2",
    "size": 599,
    "ext": "gdr2",
    "gr2": "data:embedded",
    "uploadedAt": 1777736227140
  },
  {
    "id": 19,
    "name": "Geometrical Dominator",
    "creator": "Robtop",
    "diff": "Harder",
    "section": "main",
    "filename": "geometrical dominator.gdr2",
    "size": 505,
    "ext": "gdr2",
    "gr2": "data:embedded",
    "uploadedAt": 1777736259110
  },
  {
    "id": 20,
    "name": "Deadlocked",
    "creator": "RobTop",
    "diff": "Hard Demon",
    "section": "main",
    "filename": "deadlocked.gdr2",
    "size": 643,
    "ext": "gdr2",
    "gr2": "data:embedded",
    "uploadedAt": 1777736284764
  },
  {
    "id": 21,
    "name": "FingerDash",
    "creator": "RobTop",
    "diff": "Insane",
    "section": "main",
    "filename": "FingerDash.gdr2",
    "size": 487,
    "ext": "gdr2",
    "gr2": "data:embedded",
    "uploadedAt": 1777736307190
  },
  {
    "id": 22,
    "name": "Dash",
    "creator": "RobTop",
    "diff": "Insane",
    "section": "main",
    "filename": "dash.gdr2",
    "size": 443,
    "ext": "gdr2",
    "gr2": "data:embedded",
    "uploadedAt": 1777736335135
  }
]